pycbs/Messages.py
pycbs/Windows.py
pycbs/__init__.py
pycbs/__main__.py
pycbs/ClangBuild/ClangBuild.py
pycbs/ClangBuild/ClangBuild.pyi
pycbs/ClangBuild/ClangBuildParams.py
pycbs/ClangBuild/__init__.py
pycbs/ProjectBuild/ProjectBuild.py
pycbs/ProjectBuild/ProjectBuild.pyi
pycbs/ProjectBuild/__init__.py
pycbs-0.2.0.dist-info/LICENSE
pycbs-0.2.0.dist-info/METADATA
pycbs-0.2.0.dist-info/WHEEL
pycbs-0.2.0.dist-info/top_level.txt
pycbs-0.2.0.dist-info/RECORD
