Metadata-Version: 2.1
Name: pycbs
Version: 0.2.0
Summary: CLI Project Compilation Tool
Author-email: Markada <markada.py@gmail.com>
Classifier: Programming Language :: Python :: 3.13
Classifier: License :: OSI Approved :: MIT License
Classifier: Natural Language :: Russian
Classifier: Operating System :: Microsoft :: Windows
Classifier: Intended Audience :: System Administrators
Classifier: Programming Language :: C
Classifier: Topic :: Software Development :: Build Tools
Classifier: Topic :: Software Development :: Code Generators
Classifier: Topic :: Software Development :: Code Generators
Requires-Python: >=3.13
License-File: LICENSE
Requires-Dist: rich>=13.9.4
